{
  "users": [
    {
      "name": "Humoyunmirzo",
      "email": "humoyunmirzo@gmail.com",
      "phone": "+998908480793",
      "id": 1
    },
    {
      "name": "Sherjahon",
      "email": "sherjahon@gmail.com",
      "phone": "+998901234760",
      "id": 2
    },
    {
      "name": "Temur",
      "email": "temur@gmail.com",
      "phone": "+998902134434",
      "id": 3
    },
    {
      "name": "Fotima",
      "email": "fotima@gmail.com",
      "phone": "+998903436434",
      "id": 4
    },
    {
      "name": "Xusrav",
      "email": "xusrav@gmail.com",
      "phone": "+998902122323",
      "id": 5
    }
  ]
}